setup.py
phrase_recognizer/__init__.py
phrase_recognizer/phrase_recognizer.py
phrase_recognizer/phrase_rules_split.py
phrase_recognizer.egg-info/PKG-INFO
phrase_recognizer.egg-info/SOURCES.txt
phrase_recognizer.egg-info/dependency_links.txt
phrase_recognizer.egg-info/not-zip-safe
phrase_recognizer.egg-info/requires.txt
phrase_recognizer.egg-info/top_level.txt