Metadata-Version: 1.1
Name: phrase-recognizer
Version: 0.0.1
Summary: Phrase Recognizer
Home-page: http://github.com/17zuoye/phrase_recognizer/
Author: David Chen
Author-email: mvjome@gmail.com
License: MIT
Platform: any
Classifier: Intended Audience :: Developers
Classifier: Operating System :: OS Independent
Classifier: Programming Language :: Python
Classifier: Topic :: Software Development :: Libraries :: Python Modules
